epimetheus/__init__.py
epimetheus/metrics.py
epimetheus/registry.py
epimetheus/sample.py
epimetheus-0.4.0.dist-info/LICENSE
epimetheus-0.4.0.dist-info/WHEEL
epimetheus-0.4.0.dist-info/METADATA
epimetheus-0.4.0.dist-info/RECORD
